mowaki/__init__.py
mowaki/config.py
mowaki/context.py
mowaki/crypto.py
mowaki/database.py
mowaki/email_composer.py
mowaki/jwt.py
mowaki/emailer/__init__.py
mowaki/emailer/base.py
mowaki/emailer/dummy.py
mowaki/emailer/smtp.py
mowaki/storage/__init__.py
mowaki/storage/base.py
mowaki/storage/storage_file.py
mowaki/storage/storage_memory.py
mowaki/storage/storage_s3.py
mowaki/storage/types.py
mowaki-2.0.dist-info/METADATA
mowaki-2.0.dist-info/WHEEL
mowaki-2.0.dist-info/licenses/LICENSE
mowaki-2.0.dist-info/RECORD
