Metadata-Version: 2.3
Name: mowaki
Version: 2.0
Summary: Utilities for MoWaKi (and other) apps
Project-URL: Homepage, https://www.mowaki.org
Project-URL: Repository, https://github.com/rshk/mowaki-py
Project-URL: Issues, https://github.com/rshk/mowaki-py/issues
Author-email: Sam Santi <samuele@samuelesanti.com>
License: MIT License
License-File: LICENSE
Classifier: License :: OSI Approved :: MIT License
Classifier: Operating System :: OS Independent
Classifier: Programming Language :: Python :: 3
Requires-Python: >=3.9
